bioinformatic_izsam_theme/404.html
bioinformatic_izsam_theme/__init__.py
bioinformatic_izsam_theme/base.html
bioinformatic_izsam_theme/footer.html
bioinformatic_izsam_theme/header.html
bioinformatic_izsam_theme/main.html
bioinformatic_izsam_theme/mkdocs_theme.yml
bioinformatic_izsam_theme/nav.html
bioinformatic_izsam_theme/search.html
bioinformatic_izsam_theme/css/base.css
bioinformatic_izsam_theme/css/footer.css
bioinformatic_izsam_theme/css/header.css
bioinformatic_izsam_theme/css/iconic.css
bioinformatic_izsam_theme/css/normalize.css
bioinformatic_izsam_theme/css/pygments-friendly.css
bioinformatic_izsam_theme/css/pygments-github-dark.css
bioinformatic_izsam_theme/css/pygments-rainbow-dash.css
bioinformatic_izsam_theme/css/pygments-solarized-light.css
bioinformatic_izsam_theme/css/pygments.css
bioinformatic_izsam_theme/css/skeleton.css
bioinformatic_izsam_theme/css/vars.css
bioinformatic_izsam_theme/css/wiki.css
bioinformatic_izsam_theme/fonts/Roboto_Mono/RobotoMono-Bold.ttf
bioinformatic_izsam_theme/fonts/Roboto_Mono/RobotoMono-Bold.woff
bioinformatic_izsam_theme/fonts/Roboto_Mono/RobotoMono-Bold.woff2
bioinformatic_izsam_theme/fonts/Roboto_Mono/RobotoMono-Regular.ttf
bioinformatic_izsam_theme/fonts/Roboto_Mono/RobotoMono-Regular.woff
bioinformatic_izsam_theme/fonts/Roboto_Mono/RobotoMono-Regular.woff2
bioinformatic_izsam_theme/fonts/Titillium_Web/TitilliumWeb-Bold-Italic.woff
bioinformatic_izsam_theme/fonts/Titillium_Web/TitilliumWeb-Bold-Italic.woff2
bioinformatic_izsam_theme/fonts/Titillium_Web/TitilliumWeb-Bold.woff
bioinformatic_izsam_theme/fonts/Titillium_Web/TitilliumWeb-Bold.woff2
bioinformatic_izsam_theme/fonts/Titillium_Web/TitilliumWeb-Regular-Italic.woff
bioinformatic_izsam_theme/fonts/Titillium_Web/TitilliumWeb-Regular-Italic.woff2
bioinformatic_izsam_theme/fonts/Titillium_Web/TitilliumWeb-Regular.woff
bioinformatic_izsam_theme/fonts/Titillium_Web/TitilliumWeb-Regular.woff2
mkdocs_bioinformatic_izsam_theme-1.0.13.dist-info/LICENCE.txt
mkdocs_bioinformatic_izsam_theme-1.0.13.dist-info/METADATA
mkdocs_bioinformatic_izsam_theme-1.0.13.dist-info/WHEEL
mkdocs_bioinformatic_izsam_theme-1.0.13.dist-info/entry_points.txt
mkdocs_bioinformatic_izsam_theme-1.0.13.dist-info/top_level.txt
mkdocs_bioinformatic_izsam_theme-1.0.13.dist-info/RECORD
