Metadata-Version: 2.1
Name: mkdocs-bioinformatic-izsam-theme
Version: 1.0.13
Summary: MkDocs theme designed for Bioinformatic Unit of the Istituto Zooprofilattico dell' Abruzzo e del Molise G. Caporale
Home-page: 
Author: Alessandro De Luca
Author-email: al.deluca@izs.it
License: MIT
Keywords: MkDocs,Theme,Software documentation
License-File: LICENCE.txt
Requires-Dist: mkdocs>=1.0.4
